{
  "schema_version": "1.0",
  "chronicle_id": "blueedge-governed-cognitive-replay-chronicle",
  "certification_status": "REPLAY-CERTIFIED",
  "certified_at": "2026-05-23T00:30:00Z",
  "stream": "PI.BLUEEDGE.GOVERNED-COGNITIVE-REPLAY-CHRONICLE.RC-09",
  "classification": "G1",
  "certification_checks": [
    {
      "check_id": "CERT-01",
      "description": "All 10 checkpoints (00-09) exist and status FROZEN",
      "result": "PASS",
      "details": "checkpoint_00_baseline through checkpoint_09_narrative — all present, all FROZEN"
    },
    {
      "check_id": "CERT-02",
      "description": "All 11 spine objects emitted and internally consistent",
      "result": "PASS",
      "details": "7 spine classes: evidence_object(3), executive_projection_snapshot(1), semantic_proposition_derivation(1), qualification_transition(3), replay_corridor(1), convergence_observation(1), narrative_orchestration(1)"
    },
    {
      "check_id": "CERT-03",
      "description": "REPLAY_CHRONICLE.html generated and non-empty",
      "result": "PASS",
      "details": "64,134 bytes, 8 chapters, 32 zoom levels (Z2-Z5 × 8)"
    },
    {
      "check_id": "CERT-04",
      "description": "All narrative proof capsule spine references resolve",
      "result": "PASS",
      "details": "8 proof capsules, all spine_object_refs found in spine_objects.json"
    },
    {
      "check_id": "CERT-05",
      "description": "75.x authority declaration with 13 prohibitions",
      "result": "PASS",
      "details": "narrative_authority.json: 75.x bounded interpretive, 13 absolute prohibitions (P01-P13)"
    },
    {
      "check_id": "CERT-06",
      "description": "BlueEdge promotion_state shows GOVERNED_REPLAY_QUALIFICATION",
      "result": "PASS",
      "details": "qualification_provenance: GOVERNED_REPLAY_QUALIFICATION, prior bridge provenance preserved"
    },
    {
      "check_id": "CERT-07",
      "description": "CHRONICLE_MANIFEST.json complete through RC-08",
      "result": "PASS",
      "details": "RC-01 through RC-08 all COMPLETE, spine_object_count: 11, narrative_chapter_count: 8"
    },
    {
      "check_id": "CERT-08",
      "description": "No NetBox spine objects mutated",
      "result": "PASS",
      "details": "NetBox corpus read-only throughout (convergence observations only)"
    },
    {
      "check_id": "CERT-09",
      "description": "7 convergence observations documented with 15-dimension comparison matrix",
      "result": "PASS",
      "details": "All at DESCRIPTIVE maturity, SUPPORTED_BY_BOTH_SPECIMENS"
    },
    {
      "check_id": "CERT-10",
      "description": "Full replay corridor from CP-00 (EMERGENCE) to CP-09 (PROJECTION) deterministic",
      "result": "PASS",
      "details": "10 checkpoints spanning 8 semantic phases, contiguous predecessor chain"
    }
  ],
  "total_checks": 10,
  "passed": 10,
  "failed": 0,
  "chronicle_summary": {
    "streams_completed": 9,
    "checkpoints_frozen": 10,
    "spine_objects_emitted": 12,
    "chapters_rendered": 8,
    "semantic_phases_covered": ["EMERGENCE", "FORMATION", "TENSION", "STRENGTHENING", "STABILIZATION", "QUALIFICATION", "CONVERGENCE", "PROJECTION"],
    "governance_events": 94,
    "propositions_derived": 85,
    "propositions_accepted": 71,
    "propositions_rejected": 14,
    "revalidation_checks": 48,
    "convergence_observations": 7,
    "candidate_laws": 7,
    "comparison_dimensions": 15,
    "convergent_dimensions": 8,
    "divergent_dimensions": 7,
    "qualification_transition": "S2_BRIDGE → S2_GOVERNED",
    "corridor_type": "POST_GENESIS_SEMANTIC_REPLAY"
  },
  "what_the_chronicle_proves": [
    "Governance patterns transfer across specimens with different evidence channels",
    "PATH B evidence (HTML documents) can produce governed semantic propositions",
    "Operator review generates genuine governance friction on document-derived claims",
    "Evidence enrichment strengthens propositions even without code graph access",
    "Deterministic revalidation confirms governance-driven improvement across specimen types",
    "S2_BRIDGE → S2_GOVERNED transition demonstrates governance lifecycle is specimen-independent",
    "Cross-specimen convergence establishes Program Intelligence as a discipline, not a one-specimen trick",
    "Governed cognition can be composed into navigable cognitive traversal instruments"
  ],
  "what_the_chronicle_does_not_prove": [
    "Raw intake genesis for BlueEdge (chronicle corridor is post-genesis semantic replay)",
    "More than 2-specimen pattern maturity for candidate laws (comparison, not generalization)",
    "S3 readiness or authority",
    "Marketplace, module, or agentic capabilities",
    "That the chronicle replaces governed outputs (reports, LENS views, SQO cockpit)"
  ]
}
